gabliterate/__init__.py
gabliterate/__main__.py
gabliterate/automate.py
gabliteration-0.1.0.dist-info/licenses/LICENSE
gabliteration-0.1.0.dist-info/METADATA
gabliteration-0.1.0.dist-info/WHEEL
gabliteration-0.1.0.dist-info/entry_points.txt
gabliteration-0.1.0.dist-info/top_level.txt
gabliteration-0.1.0.dist-info/RECORD
