Metadata-Version: 2.4
Name: gabliteration
Version: 0.1.0
Summary: Automated Gabliteration
Home-page: https://github.com/Goekdeniz-Guelmez/gabliteration
Author: Gökdeniz Gülmez
License: MIT
Requires-Python: >=3.8
License-File: LICENSE
Requires-Dist: torch
Requires-Dist: transformers>=4.39.3
Requires-Dist: datasets
Requires-Dist: tqdm
Requires-Dist: numpy
Dynamic: author
Dynamic: description
Dynamic: description-content-type
Dynamic: home-page
Dynamic: license
Dynamic: license-file
Dynamic: requires-dist
Dynamic: requires-python
Dynamic: summary
